{"cameraMode":{"drawMode":0,"name":"Shaded","section":"Shading Mode"},"sceneLighting":false,"audioPlay":false,"sceneViewState":{"m_AlwaysRefresh":false,"showFog":true,"showSkybox":false,"showFlares":true,"showImageEffects":true,"showParticleSystems":true,"showVisualEffectGraphs":true,"m_FxEnabled":true},"in2DMode":false,"pivot":{"x":474.8134460449219,"y":334.5647888183594,"z":-6.16796875},"rotation":{"x":-0.07462078332901001,"y":-0.0033092680387198927,"z":-0.0003026524791494012,"w":0.9972293972969055},"size":312.66571044921877,"orthographic":false}